aiorpcx/__init__.py
aiorpcx/curio.py
aiorpcx/framing.py
aiorpcx/jsonrpc.py
aiorpcx/rawsocket.py
aiorpcx/session.py
aiorpcx/socks.py
aiorpcx/unixsocket.py
aiorpcx/util.py
aiorpcx/websocket.py
aiorpcX-0.24.0.dist-info/LICENCE
aiorpcX-0.24.0.dist-info/METADATA
aiorpcX-0.24.0.dist-info/WHEEL
aiorpcX-0.24.0.dist-info/top_level.txt
aiorpcX-0.24.0.dist-info/RECORD
