Metadata-Version: 2.2
Name: aiorpcX
Version: 0.24.0
Summary: Generic async RPC implementation, including JSON-RPC
Download-URL: https://github.com/kyuupichan/aiorpcX/archive/0.24.0.tar.gz
Author-email: Neil Booth <kyuupichan@pm.me>
License: Copyright (c) 2018 Neil Booth
Project-URL: Project-URL, https://github.com/kyuupichan/aiorpcX
Classifier: Development Status :: 4 - Beta
Classifier: Framework :: AsyncIO
Classifier: Intended Audience :: Developers
Classifier: License :: OSI Approved :: MIT License
Classifier: Operating System :: OS Independent
Classifier: Programming Language :: Python :: 3.9
Classifier: Topic :: Internet
Classifier: Topic :: Software Development :: Libraries :: Python Modules
Requires-Python: >=3.9
License-File: LICENCE
Provides-Extra: ws
Requires-Dist: websockets>=14.0; extra == "ws"
Dynamic: description
Dynamic: download-url
Dynamic: requires-python
